bqat/__init__.py
bqat/__main__.py
bqat/cli.py
bqat/utils.py
bqat-1.8.4.dist-info/WHEEL
bqat-1.8.4.dist-info/entry_points.txt
bqat-1.8.4.dist-info/METADATA
bqat-1.8.4.dist-info/RECORD
