Metadata-Version: 2.4
Name: bqat
Version: 1.8.4
Summary: Biometric Quality Assessment Tool - CLI (BQAT-CLI)
Keywords: bqat,cli,biometric
Author: Liam Wu
Author-email: Liam Wu <liam.wu@biometix.com>
License-Expression: Apache-2.0
Classifier: Development Status :: 4 - Beta
Classifier: Environment :: Console
Classifier: Intended Audience :: Science/Research
Classifier: Intended Audience :: Information Technology
Classifier: Intended Audience :: Developers
Classifier: Operating System :: OS Independent
Classifier: License :: OSI Approved :: Apache Software License
Classifier: Programming Language :: Python
Classifier: Programming Language :: Python :: 3.10
Classifier: Programming Language :: Python :: 3.11
Classifier: Programming Language :: Python :: 3.12
Classifier: Programming Language :: Python :: 3.13
Classifier: Programming Language :: Python :: 3.14
Classifier: Programming Language :: Python :: 3 :: Only
Classifier: Topic :: Scientific/Engineering :: Information Analysis
Classifier: Topic :: Scientific/Engineering :: Image Processing
Classifier: Topic :: Scientific/Engineering :: Artificial Intelligence
Requires-Python: >=3.10, <3.15
Project-URL: Changelog, https://biometix.github.io/changelog/#bqat-cli
Project-URL: Documentation, https://biometix.github.io/getting_started/cli.html
Project-URL: Issues, https://github.com/Biometix/bqat-cli/discussions
Project-URL: Releases, https://github.com/Biometix/bqat-cli/releases
Project-URL: Repository, https://github.com/Biometix/bqat-cli
